<!--
  Copyright (c) 2019 OPPO Technologies, Inc.
  All Rights Reserved.
  Confidential and Proprietary - OPPO Technologies, Inc.
-->
<!--
CameraEngmodeConfig :
    This node must be added for each module prosent in the device.
    It contain all information about the module present.
    The number of nodes of CameraEngmodeConfig indicate number of modules
    to be probed on the device.
    Maximum number of CameraEngmodeConfig nodes is 10
- - - - - - - - - - - - - - - - - - - - - - - - - - - - - - - - - - - - - - - -
-->
<CameraEngmodeRoot>
  <CameraEngmodeConfig>
    <CameraId>0</CameraId>
    <SensorName>imx586</SensorName>
    <isAvailable>true</isAvailable>
    <OisCalib>
      <xGyroOffsetAddr>0x8455</xGyroOffsetAddr>
      <yGyroOffsetAddr>0x8456</yGyroOffsetAddr>
      <xGyroOffsetCalibAddr>0x8406</xGyroOffsetCalibAddr>
      <yGyroOffsetCalibAddr>0x8486</yGyroOffsetCalibAddr>
      <regAddrType>2</regAddrType>
      <regDataType>2</regDataType>
    </OisCalib>
    <eepromCalib>
      <isAvailable>true</isAvailable>
      <MWdata>
        <devIndex>10</devIndex>
        <isWRP>0x1</isWRP>
        <isAvailable>true</isAvailable>
        <dataAddress>0x2600</dataAddress>
        <offset>0x2600</offset>
        <dataSize>1689</dataSize>
      </MWdata>
      <MTdata>
        <devIndex>10</devIndex>
        <isWRP>0x1</isWRP>
        <isAvailable>true</isAvailable>
        <dataAddress>0x2D00</dataAddress>
        <offset>0x2D00</offset>
        <dataSize>1689</dataSize>
      </MTdata>
      <AEsyncdata>
        <devIndex>10</devIndex>
        <isWRP>0x1</isWRP>
        <isAvailable>true</isAvailable>
        <dataAddress>0x3400</dataAddress>
        <offset>0x3400</offset>
        <dataSize>36</dataSize>
      </AEsyncdata>
      <SN>
        <devIndex>0x01</devIndex>
        <isWRP>0</isWRP>
        <isAvailable>true</isAvailable>
        <dataAddress>0x00B0</dataAddress>
        <offset>0x00B0</offset>
        <dataSize>17</dataSize>
      </SN>
      <Distortiondata>
        <devIndex>10</devIndex>
        <isWRP>0</isWRP>
        <isAvailable>false</isAvailable>
        <dataAddress>0x2600</dataAddress>
        <dataSize>36</dataSize>
      </Distortiondata>
	</eepromCalib>
  </CameraEngmodeConfig>
  <CameraEngmodeConfig>
    <CameraId>1</CameraId>
    <SensorName>imx708</SensorName>
    <isAvailable>true</isAvailable>
    <eepromCalib>
      <isAvailable>true</isAvailable>
      <MWdata>
          <devIndex>11</devIndex>
          <isWRP>0x1</isWRP>
          <isAvailable>true</isAvailable>
          <dataAddress>0x540</dataAddress>
          <offset>0x540</offset>
          <dataSize>1561</dataSize>
      </MWdata>
      <MTdata>
          <devIndex>11</devIndex>
          <isWRP>0x1</isWRP>
          <isAvailable>false</isAvailable>
          <dataAddress>0x540</dataAddress>
          <offset>0x540</offset>
          <dataSize>1561</dataSize>
      </MTdata>
      <AEsyncdata>
          <devIndex>11</devIndex>
          <isWRP>0x1</isWRP>
          <isAvailable>true</isAvailable>
          <dataAddress>0xC00</dataAddress>
          <offset>0xC00</offset>
          <dataSize>36</dataSize>
      </AEsyncdata>
      <SN>
          <devIndex>0x02</devIndex>
          <isWRP>0</isWRP>
          <isAvailable>true</isAvailable>
          <dataAddress>0x00B0</dataAddress>
          <offset>0x00B0</offset>
          <dataSize>17</dataSize>
      </SN>
      <Distortiondata>
          <devIndex>11</devIndex>
          <isWRP>0</isWRP>
          <isAvailable>true</isAvailable>
          <dataAddress>0x1E20</dataAddress>
          <offset>0x1E20</offset>
          <dataSize>3441</dataSize>
      </Distortiondata>
    </eepromCalib>
  </CameraEngmodeConfig>
  <CameraEngmodeConfig>
    <CameraId>2</CameraId>
    <SensorName>imx616</SensorName>
    <isAvailable>false</isAvailable>
    <eepromCalib>
      <isAvailable>false</isAvailable>
      <MWdata>
        <devIndex>14</devIndex>
        <isWRP>0x00</isWRP>
        <isAvailable>false</isAvailable>
        <dataAddress>0x18FC</dataAddress>
        <noNeedWrEEprom>false</noNeedWrEEprom>
        <offset>0x18FC</offset>
        <dataSize>128</dataSize>
      </MWdata>
      <MTdata>
        <devIndex>14</devIndex>
        <isWRP>0x01</isWRP>
        <isAvailable>false</isAvailable>
        <dataAddress>0x18FC</dataAddress>
        <offset>0x18FC</offset>
        <dataSize>128</dataSize>
      </MTdata>
      <AEsyncdata>
        <devIndex>14</devIndex>
        <isWRP>0x01</isWRP>
        <isAvailable>false</isAvailable>
        <dataAddress>0x1980</dataAddress>
        <offset>6528</offset>
        <dataSize>40</dataSize>
      </AEsyncdata>
      <SN>
        <devIndex>0x01</devIndex>
        <isWRP>0</isWRP>
        <isAvailable>false</isAvailable>
        <dataAddress>0x1C0A</dataAddress>
        <offset>40</offset>
        <dataSize>17</dataSize>
      </SN>
      <Distortiondata>
        <devIndex>14</devIndex>
        <isWRP>0</isWRP>
        <isAvailable>false</isAvailable>
        <dataAddress>0x66A</dataAddress>
        <offset>40</offset>
        <dataSize>17</dataSize>
      </Distortiondata>
    </eepromCalib>
  </CameraEngmodeConfig>
  <CameraEngmodeConfig>
    <CameraId>3</CameraId>
    <SensorName>s5k3m5</SensorName>
    <isAvailable>true</isAvailable>
    <eepromCalib>
      <isAvailable>true</isAvailable>
      <MWdata>
        <devIndex>13</devIndex>
        <isWRP>0x00</isWRP>
        <isAvailable>false</isAvailable>
        <dataAddress>0x530</dataAddress>
        <offset>0x530</offset>
        <dataSize>1561</dataSize>
      </MWdata>
      <MTdata>
        <devIndex>13</devIndex>
        <isWRP>0x0</isWRP>
        <isAvailable>true</isAvailable>
        <dataAddress>0x540</dataAddress>
        <offset>0x540</offset>
        <dataSize>1561</dataSize>
      </MTdata>
      <AEsyncdata>
        <devIndex>13</devIndex>
        <isWRP>0x0</isWRP>
        <isAvailable>true</isAvailable>
        <dataAddress>0xC80</dataAddress>
        <offset>0xC80</offset>
        <dataSize>36</dataSize>
      </AEsyncdata>
      <SN>
        <devIndex>0x03</devIndex>
        <isWRP>0</isWRP>
        <isAvailable>true</isAvailable>
        <dataAddress>0x00B0</dataAddress>
        <offset>0x00B0</offset>
        <dataSize>17</dataSize>
      </SN>
      <Distortiondata>
        <devIndex>13</devIndex>
        <isWRP>0x00</isWRP>
        <isAvailable>false</isAvailable>
        <dataAddress>0x2600</dataAddress>
        <offset>0x1E20</offset>
        <dataSize>36</dataSize>
      </Distortiondata>
    </eepromCalib>
  </CameraEngmodeConfig>
</CameraEngmodeRoot>
